{
  "rooms": [
    {
      "id": 0,
      "name": "Test room",
      "password": "testPass",
      "users": [
        [
          "Sai",
          75
        ]
      ],
      "tasks": [
        {
          "title": "task title",
          "description": "task desc",
          "value": 5,
          "achieved": [
            "Max",
            "Sai",
          ],
          "redo": true
        },
        {
          "title": "high-worth task",
          "description": "many points",
          "value": 15,
          "achieved": [
            "Max",
            "Sai",
          ],
          "redo": false
        }
      ]
    }
  ]
}